LICENSE
MANIFEST.in
Makefile
README.md
requirements.txt
setup.py
gmtb/__init__.py
gmtb.egg-info/PKG-INFO
gmtb.egg-info/SOURCES.txt
gmtb.egg-info/dependency_links.txt
gmtb.egg-info/requires.txt
gmtb.egg-info/top_level.txt
gmtb/dpe/__init__.py
gmtb/dpe/best_weighted_mean.py
gmtb/dpe/compute_alpha.py
gmtb/dpe/compute_median.py
gmtb/dpe/compute_median_vector.py
gmtb/dpe/embed.py
gmtb/dpe/minimum_sphere.py
gmtb/dpe/reconstruct.py
gmtb/dpe/embedding/__init__.py
gmtb/dpe/embedding/cca.py
gmtb/dpe/embedding/fastmap.py
gmtb/dpe/embedding/metricmap.py
gmtb/dpe/embedding/prototype.py
gmtb/dpe/embedding/sammon.py
gmtb/dpe/embedding/sparsemap.py
gmtb/dpe/reconstruction/__init__.py
gmtb/dpe/reconstruction/best_recursive.py
gmtb/dpe/reconstruction/linear.py
gmtb/dpe/reconstruction/linear_recursive.py
gmtb/dpe/reconstruction/triangular_recursive.py
gmtb/ewm/__init__.py
gmtb/ewm/ewm.py
gmtb/kernel/__init__.py
gmtb/kernel/best_weighted_mean.py
gmtb/kernel/compute_alpha.py
gmtb/kernel/compute_median.py
gmtb/kernel/compute_weights.py
gmtb/kernel/kernel_functions/__init__.py
gmtb/kernel/kernel_functions/cluster_kernel.py
gmtb/kernel/kernel_functions/dist_sub.py
gmtb/kernel/kernel_functions/edit_distance_kernel.py
gmtb/kernel/kernel_functions/kendall_kernel.py
gmtb/kernel/kernel_functions/partition_kernel.py
gmtb/kernel/reconstruction/__init__.py
gmtb/kernel/reconstruction/linear.py
gmtb/kernel/reconstruction/linear_recursive.py
gmtb/kernel/reconstruction/triangular_recursive.py
gmtb/util/__init__.py
gmtb/util/k_medians.py
gmtb/util/linear_search.py
gmtb/util/lower_bound.py
gmtb/util/pdist.py
gmtb/util/distance/__init__.py
gmtb/util/distance/euclidean_dist.py
gmtb/util/distance/kendall_tau_dist.py
gmtb/util/distance/kendall_tau_dist_cy.pyx
gmtb/util/distance/partition_dist.py
gmtb/util/distance/string_edit_dist.py
test/example.py