Metadata-Version: 2.1
Name: gmtb
Version: 1.0.5
Summary: Python version of the Generalized Median Toolbox.
Home-page: https://www.uni-muenster.de/PRIA/en/forschung/dpe.html
Author: Andreas Nienkötter
Author-email: a.nienkoetter@uni-muenster.de
License: MIT
Platform: UNKNOWN
Classifier: License :: OSI Approved :: MIT License
Classifier: Programming Language :: Python :: 3
